pppoetry_demo/__init__.py
pppoetry_demo/pppoetry_demo.py
pppoetry_demo-0.1.6.dist-info/entry_points.txt
pppoetry_demo-0.1.6.dist-info/WHEEL
pppoetry_demo-0.1.6.dist-info/METADATA
pppoetry_demo-0.1.6.dist-info/RECORD
