Metadata-Version: 2.1
Name: pppoetry-demo
Version: 0.1.6
Summary: 
Author: neilbaldwin
Author-email: neil.baldwin@mac.com
Requires-Python: >=3.9,<4.0
Classifier: Programming Language :: Python :: 3
Classifier: Programming Language :: Python :: 3.9
Requires-Dist: pendulum (>=2.1.2,<3.0.0)
